{
  "pools": [
    {
      "rolls": 1,
      "bonus_rolls": 0,
      "entries": [
        {
          "type": "minecraft:item",
          "name": "minecraft:ender_dragon_spawn_egg",
          "functions": [
            {
              "function": "minecraft:set_components",
              "components": {
                "custom_data": {
                  "stellarity:item": "voided_zombie_spawn_egg"
                },
                "minecraft:item_name": {
                  "translate": "item.stellarity.voided_zombie_spawn_egg"
                },
                "minecraft:entity_data": {
                  "id": "minecraft:marker",
                  "Tags": [
                    "stellarity.spawn_egg",
                    "smithed.entity",
                    "smithed.strict"
                  ],
                  "data": {
                    "mob": "voided_zombie"
                  }
                },
                "rarity": "common"
              }
            }
          ]
        }
      ]
    }
  ]
}
